senml/__init__.py
senml/senml_base.py
senml/senml_pack.py
senml/senml_record.py
senml/senml_unit.py
micropython_senml-0.1.0.dist-info/METADATA
micropython_senml-0.1.0.dist-info/WHEEL
micropython_senml-0.1.0.dist-info/RECORD
