Metadata-Version: 2.1
Name: micropython-senml
Version: 0.1.0
Summary: SenML serialisation for MicroPython.
Project-URL: Homepage, https://github.com/micropython/micropython-lib
Author-email: micropython-lib <contact@micropython.org>
License: 0.1.0
Requires-Dist: cbor2
